{
    "Tags": [
        {
            "Key": "owner",
            "Value": "comp9323"
        },
        {
            "Key": "country",
            "Value": "australia"
        },
        {
            "Key": "business_unit",
            "Value": "consulting"
        }
    ],
    "ResponseMetadata": {
        "RequestId": "JTU49KFD2BFQ9LMIF019U9VIJFVV4KQNSO5AEMVJF66Q9ASUAAJG",
        "HTTPStatusCode": 200,
        "HTTPHeaders": {
            "server": "Server",
            "date": "Sun, 07 Aug 2022 11:17:56 GMT",
            "content-type": "application/x-amz-json-1.0",
            "content-length": "128",
            "connection": "keep-alive",
            "x-amzn-requestid": "JTU49KFD2BFQ9LMIF019U9VIJFVV4KQNSO5AEMVJF66Q9ASUAAJG",
            "x-amz-crc32": "1784174645"
        },
        "RetryAttempts": 0
    }
}